pySODM/__init__.py
pySODM/models/__init__.py
pySODM/models/base.py
pySODM/models/utils.py
pySODM/models/validation.py
pySODM/optimization/__init__.py
pySODM/optimization/mcmc.py
pySODM/optimization/nelder_mead.py
pySODM/optimization/objective_functions.py
pySODM/optimization/pso.py
pySODM/optimization/utils.py
pySODM/optimization/visualization.py
pysodm-0.2.9.dist-info/METADATA
pysodm-0.2.9.dist-info/WHEEL
pysodm-0.2.9.dist-info/top_level.txt
pysodm-0.2.9.dist-info/RECORD
