Metadata-Version: 2.4
Name: pySODM
Version: 0.2.9
Summary: Simulating and Optimising Dynamical Models
Home-page: https://github.com/twallema/pySODM
Author: Tijs Alleman (Ghent University, Cornell University)
Author-email: tijs.alleman@ugent.be, twa27@cornell.edu
License: CC-BY-NC-SA
Keywords: ODE PDE simulation calibration gillespie xarray emcee
Requires-Python: >3.11.11
Requires-Dist: scipy
Requires-Dist: numpy
Requires-Dist: pandas
Requires-Dist: matplotlib
Requires-Dist: xarray
Requires-Dist: emcee
Requires-Dist: h5py
Requires-Dist: tqdm
Provides-Extra: develop
Requires-Dist: pytest; extra == "develop"
Requires-Dist: sphinx; extra == "develop"
Requires-Dist: setuptools; extra == "develop"
Requires-Dist: numpydoc; extra == "develop"
Requires-Dist: sphinx_rtd_theme; extra == "develop"
Requires-Dist: myst_parser[sphinx]; extra == "develop"
Dynamic: author
Dynamic: author-email
Dynamic: description
Dynamic: description-content-type
Dynamic: home-page
Dynamic: keywords
Dynamic: license
Dynamic: provides-extra
Dynamic: requires-dist
Dynamic: requires-python
Dynamic: summary
